beancountswedbank/__init__.py
beancountswedbank/importer.py
beancountswedbank-1.0.1.dist-info/licenses/LICENSE
beancountswedbank-1.0.1.dist-info/METADATA
beancountswedbank-1.0.1.dist-info/WHEEL
beancountswedbank-1.0.1.dist-info/top_level.txt
beancountswedbank-1.0.1.dist-info/RECORD
