Metadata-Version: 2.4
Name: beancountswedbank
Version: 1.0.1
Summary: CSV importer script from Swedbank online banking for beancount
Author-email: R <contact+beancount-swedbank@vonshednob.cc>
License: MIT License
Project-URL: repository, https://codeberg.org/vonshednob/beancount-swedbank-importer
Project-URL: issues, https://codeberg.org/vonshednob/beancountswedbank/issues
Requires-Python: >=3.9
License-File: LICENSE
Requires-Dist: beangulp>=0.2.0
Dynamic: license-file
